mfisp/__init__.py
mfisp/__main__.py
mfisp/autorotate/__init__.py
mfisp/autorotate/__main__.py
mfisp/boxcrop/__init__.py
mfisp/boxcrop/__main__.py
mfisp/registration/__init__.py
mfisp/registration/__main__.py
mfisp-0.0.1.dev1.dist-info/DESCRIPTION.rst
mfisp-0.0.1.dev1.dist-info/METADATA
mfisp-0.0.1.dev1.dist-info/RECORD
mfisp-0.0.1.dev1.dist-info/WHEEL
mfisp-0.0.1.dev1.dist-info/metadata.json
mfisp-0.0.1.dev1.dist-info/top_level.txt
