Metadata-Version: 2.0
Name: mfisp
Version: 0.0.1.dev1
Summary: microfluidic image stack processing, currently contains two tools: for registration, for auto-rotation
Home-page: https://github.com/csachs/mfisp
Author: Christian C. Sachs
Author-email: sachs.christian@gmail.com
License: BSD
Platform: UNKNOWN
Classifier: Development Status :: 4 - Beta
Classifier: License :: OSI Approved :: BSD License
Classifier: Programming Language :: Python :: 3
Requires-Dist: mfisp-boxdetection
Requires-Dist: molyso
